aws_s3_settings/__init__.py
aws_s3_settings-0.0.2.dist-info/LICENSE
aws_s3_settings-0.0.2.dist-info/METADATA
aws_s3_settings-0.0.2.dist-info/WHEEL
aws_s3_settings-0.0.2.dist-info/entry_points.txt
aws_s3_settings-0.0.2.dist-info/top_level.txt
aws_s3_settings-0.0.2.dist-info/RECORD
