Metadata-Version: 2.1
Name: aws-s3-settings
Version: 0.0.2
Summary: UNKNOWN
Home-page: https://github.com/plecto/aws-s3-settings/
Author: Kristian Øllegaard
Author-email: kristian@plecto.com
License: MIT
Platform: UNKNOWN
Requires-Dist: PyYAML
Requires-Dist: boto3
